{
  "months": [
    {
      "en": {
        "ascii": "January"
      },
      "fr": {
        "ascii": "janvier"
      },
      "es": {
        "ascii": "enero"
      }
    },
    {
      "en": {
        "ascii": "February"
      },
      "fr": {
        "text": "février"
      },
      "es": {
        "ascii": "febrero"
      }
    },
    {
      "en": {
        "ascii": "March"
      },
      "fr": {
        "ascii": "mars"
      },
      "es": {
        "ascii": "marzo"
      }
    },
    {
      "en": {
        "ascii": "April"
      },
      "fr": {
        "ascii": "avril"
      },
      "es": {
        "ascii": "abril"
      }
    },
    {
      "en": {
        "ascii": "May"
      },
      "fr": {
        "ascii": "mai"
      },
      "es": {
        "ascii": "mayo"
      }
    },
    {
      "en": {
        "ascii": "June"
      },
      "fr": {
        "ascii": "juin"
      },
      "es": {
        "ascii": "junio"
      }
    },
    {
      "en": {
        "ascii": "July"
      },
      "fr": {
        "ascii": "juillet"
      },
      "es": {
        "ascii": "julio"
      }
    },
    {
      "en": {
        "ascii": "August"
      },
      "fr": {
        "text": "août"
      },
      "es": {
        "ascii": "agosto"
      }
    },
    {
      "en": {
        "ascii": "September"
      },
      "fr": {
        "ascii": "septembre"
      },
      "es": {
        "ascii": "septiembre"
      }
    },
    {
      "en": {
        "ascii": "October"
      },
      "fr": {
        "ascii": "octobre"
      },
      "es": {
        "ascii": "octubre"
      }
    },
    {
      "en": {
        "ascii": "November"
      },
      "fr": {
        "ascii": "novembre"
      },
      "es": {
        "ascii": "noviembre"
      }
    },
    {
      "en": {
        "ascii": "December"
      },
      "fr": {
        "text": "décembre"
      },
      "es": {
        "ascii": "diciembre"
      }
    }
  ]
}